GhostScan/CalibMain.py
GhostScan/Calibration.py
GhostScan/CalibrationSession.py
GhostScan/Camera.py
GhostScan/CaptureSession.py
GhostScan/ImageProcessing.py
GhostScan/Projection.py
GhostScan/Visualization.py
GhostScan/__init__.py
GhostScan/main.py
GhostScan/Calibrations/Camera2ScreenCalib.py
GhostScan/Calibrations/GeometricCalibration.py
GhostScan/Calibrations/IntrinsicCalibration.py
GhostScan/Calibrations/RadiometricCalibration.py
GhostScan/Calibrations/__init__.py
GhostScan/Calibrations/charucoMarkerCalib.py
GhostScan/Calibrations/geocalib.py
GhostScan/Calibrations/geocalibII.py
GhostScan/CalibrationsSessions/GeometricCalibSession.py
GhostScan/CalibrationsSessions/IntrinsicCalibSession.py
GhostScan/CalibrationsSessions/RadiometricCalibDisplaySession.py
GhostScan/CalibrationsSessions/RadiometricCalibSession.py
GhostScan/CalibrationsSessions/__init__.py
GhostScan/Cameras/CamControl.py
GhostScan/Cameras/Camera.py
GhostScan/Cameras/IpCam.py
GhostScan/Cameras/MachineVision.py
GhostScan/Cameras/NoCamera.py
GhostScan/Cameras/Polarization.py
GhostScan/Cameras/PySpinCapture.py
GhostScan/Cameras/Raspberry.py
GhostScan/Cameras/Webcam.py
GhostScan/Cameras/__init__.py
GhostScan/Cameras/liveDisplay.py
GhostScan/CaptureSessions/DeflectometryCapture.py
GhostScan/CaptureSessions/GradientIlluminationCapture.py
GhostScan/CaptureSessions/__init__.py
GhostScan/Projections/MainScreen.py
GhostScan/Projections/Pattern.py
GhostScan/Projections/__init__.py
GhostScan/Reconstructions/GradientIlluminationReconstruction.py
GhostScan/Reconstructions/Mesh.py
GhostScan/Reconstructions/PMD.py
GhostScan/Reconstructions/__init__.py
GhostScan/Reconstructions/generatephase.py
GhostScan/Reconstructions/normal2RGB.py
GhostScan/Reconstructions/normalInWorld.py
GhostScan-0.5.28.dist-info/METADATA
GhostScan-0.5.28.dist-info/WHEEL
GhostScan-0.5.28.dist-info/top_level.txt
GhostScan-0.5.28.dist-info/RECORD
